python_fisco/__init__.py
python_fisco/api_validator.py
python_fisco/error.py
python_fisco/private_api.py
python_fisco/public_api.py
python_fisco-0.0.7.dist-info/METADATA
python_fisco-0.0.7.dist-info/RECORD
python_fisco-0.0.7.dist-info/WHEEL
python_fisco-0.0.7.dist-info/top_level.txt
tests/__init__.py
tests/test_package.py
tests/test_private_api.py
tests/test_public_api.py
