Metadata-Version: 2.1
Name: python-fisco
Version: 0.0.7
Summary: Lib for fisco Private and Public API
Home-page: https://bitbucket.org/smapira/python-fisco/
Author: smapira
Author-email: smapira@routeflags.com
License: UNKNOWN
Keywords: trading,bitcoin,japan,API,exchange
Platform: UNKNOWN
Classifier: Programming Language :: Python :: 3
Classifier: License :: OSI Approved :: MIT License
Classifier: Operating System :: OS Independent
Requires-Dist: requests
Requires-Dist: cerberus
